swashbookler/__init__.py
swashbookler/__main__.py
swashbookler/cli.py
swashbookler/core.py
swashbookler/exceptions.py
swashbookler-1.0.2.dist-info/entry_points.txt
swashbookler-1.0.2.dist-info/LICENSE
swashbookler-1.0.2.dist-info/WHEEL
swashbookler-1.0.2.dist-info/METADATA
swashbookler-1.0.2.dist-info/RECORD
